[
  {
    "direction": "FortyFiveUp", 
    "noise": 1, 
    "sysTime": "2016-03-17T10:57:01.049-0700", 
    "xDrip_calculated_value": 138, 
    "xDrip_raw": 146, 
    "dateString": "2016-03-17T10:57:01.049-0700", 
    "sgv": 138, 
    "date": 1458237421049, 
    "xDrip_filtered": 139, 
    "xDrip_age_adjusted_raw_value": 146, 
    "unfiltered": 146000, 
    "rssi": 100, 
    "device": "xDrip-DexcomShare", 
    "filtered": 139000, 
    "xDrip_calculated_current_slope": 2.0003734030352334e-05, 
    "_id": "56eaf00a65110bbfc19276a7", 
    "type": "sgv"
  }, 
  {
    "direction": "FortyFiveUp", 
    "noise": 1, 
    "sysTime": "2016-03-17T10:52:01.105-0700", 
    "xDrip_calculated_value": 132, 
    "xDrip_raw": 141, 
    "dateString": "2016-03-17T10:52:01.105-0700", 
    "sgv": 132, 
    "date": 1458237121105, 
    "xDrip_filtered": 134, 
    "xDrip_age_adjusted_raw_value": 141, 
    "unfiltered": 141000, 
    "rssi": 100, 
    "device": "xDrip-DexcomShare", 
    "filtered": 134000, 
    "xDrip_calculated_current_slope": 1.666400042659841e-05, 
    "_id": "56eaeedd65110bbfc19276a6", 
    "type": "sgv"
  }, 
  {
    "direction": "FortyFiveUp", 
    "noise": 1, 
    "sysTime": "2016-03-17T10:47:01.057-0700", 
    "xDrip_calculated_value": 127, 
    "xDrip_raw": 137, 
    "dateString": "2016-03-17T10:47:01.057-0700", 
    "sgv": 127, 
    "date": 1458236821057, 
    "xDrip_filtered": 129, 
    "xDrip_age_adjusted_raw_value": 137, 
    "unfiltered": 137000, 
    "rssi": 100, 
    "device": "xDrip-DexcomShare", 
    "filtered": 129000, 
    "xDrip_calculated_current_slope": 1.6672668827444548e-05, 
    "_id": "56eaedd265110bbfc19276a5", 
    "type": "sgv"
  }, 
  {
    "direction": "FortyFiveUp", 
    "noise": 1, 
    "sysTime": "2016-03-17T10:42:01.165-0700", 
    "xDrip_calculated_value": 122, 
    "xDrip_raw": 132, 
    "dateString": "2016-03-17T10:42:01.165-0700", 
    "sgv": 122, 
    "date": 1458236521165, 
    "xDrip_filtered": 124, 
    "xDrip_age_adjusted_raw_value": 132, 
    "unfiltered": 132000, 
    "rssi": 100, 
    "device": "xDrip-DexcomShare", 
    "filtered": 124000, 
    "xDrip_calculated_current_slope": 1.6688862854262836e-05, 
    "_id": "56eaec8565110bbfc19276a4", 
    "type": "sgv"
  }, 
  {
    "direction": "FortyFiveUp", 
    "noise": 1, 
    "sysTime": "2016-03-17T10:37:01.564-0700", 
    "xDrip_calculated_value": 117, 
    "xDrip_raw": 127, 
    "dateString": "2016-03-17T10:37:01.564-0700", 
    "sgv": 117, 
    "date": 1458236221564, 
    "xDrip_filtered": 119, 
    "xDrip_age_adjusted_raw_value": 127, 
    "unfiltered": 127000, 
    "rssi": 100, 
    "device": "xDrip-DexcomShare", 
    "filtered": 119000, 
    "xDrip_calculated_current_slope": 1.9974831712042826e-05, 
    "_id": "56eaeb8665110bbfc19276a3", 
    "type": "sgv"
  }, 
  {
    "direction": "FortyFiveUp", 
    "noise": 1, 
    "sysTime": "2016-03-17T10:32:01.186-0700", 
    "xDrip_calculated_value": 111, 
    "xDrip_raw": 122, 
    "dateString": "2016-03-17T10:32:01.186-0700", 
    "sgv": 111, 
    "date": 1458235921186, 
    "xDrip_filtered": 114, 
    "xDrip_age_adjusted_raw_value": 122, 
    "unfiltered": 122000, 
    "rssi": 100, 
    "device": "xDrip-DexcomShare", 
    "filtered": 114000, 
    "xDrip_calculated_current_slope": 2.3346640918656966e-05, 
    "_id": "56eaea3465110bbfc19276a2", 
    "type": "sgv"
  }, 
  {
    "direction": "Flat", 
    "noise": 1, 
    "sysTime": "2016-03-17T10:27:01.357-0700", 
    "xDrip_calculated_value": 104, 
    "xDrip_raw": 116, 
    "dateString": "2016-03-17T10:27:01.357-0700", 
    "sgv": 104, 
    "date": 1458235621357, 
    "xDrip_filtered": 109, 
    "xDrip_age_adjusted_raw_value": 116, 
    "unfiltered": 116000, 
    "rssi": 100, 
    "device": "xDrip-DexcomShare", 
    "filtered": 109000, 
    "xDrip_calculated_current_slope": 1.66347833319471e-05, 
    "_id": "56eae92c65110bbfc19276a1", 
    "type": "sgv"
  }, 
  {
    "direction": "Flat", 
    "noise": 1, 
    "sysTime": "2016-03-17T10:22:00.782-0700", 
    "xDrip_calculated_value": 99, 
    "xDrip_raw": 112, 
    "dateString": "2016-03-17T10:22:00.782-0700", 
    "sgv": 99, 
    "date": 1458235320782, 
    "xDrip_filtered": 105, 
    "xDrip_age_adjusted_raw_value": 112, 
    "unfiltered": 112000, 
    "rssi": 100, 
    "device": "xDrip-DexcomShare", 
    "filtered": 105000, 
    "xDrip_calculated_current_slope": 1.0013317712557701e-05, 
    "_id": "56eae7db65110bbfc192769d", 
    "type": "sgv"
  }, 
  {
    "direction": "Flat", 
    "noise": 1, 
    "sysTime": "2016-03-17T10:17:01.181-0700", 
    "xDrip_calculated_value": 96, 
    "xDrip_raw": 109, 
    "dateString": "2016-03-17T10:17:01.181-0700", 
    "sgv": 96, 
    "date": 1458235021181, 
    "xDrip_filtered": 104, 
    "xDrip_age_adjusted_raw_value": 109, 
    "unfiltered": 109000, 
    "rssi": 100, 
    "device": "xDrip-DexcomShare", 
    "filtered": 104000, 
    "xDrip_calculated_current_slope": 1.33232520725984e-05, 
    "_id": "56eae6d365110bbfc192769c", 
    "type": "sgv"
  }, 
  {
    "direction": "FortyFiveDown", 
    "noise": 1, 
    "sysTime": "2016-03-17T10:12:00.954-0700", 
    "xDrip_calculated_value": 92, 
    "xDrip_raw": 105, 
    "dateString": "2016-03-17T10:12:00.954-0700", 
    "sgv": 92, 
    "date": 1458234720954, 
    "xDrip_filtered": 108, 
    "xDrip_age_adjusted_raw_value": 105, 
    "unfiltered": 105000, 
    "rssi": 100, 
    "device": "xDrip-DexcomShare", 
    "filtered": 108000, 
    "xDrip_calculated_current_slope": 3.3375386320096657e-06, 
    "_id": "56eae58265110bbfc1927699", 
    "type": "sgv"
  }
]