[
  {
    "_type": "BasalProfileStart", 
    "_description": "BasalProfileStart 2016-03-02T11:00:00 head[2], body[3] op[0x7b]", 
    "timestamp": "2016-03-02T11:00:00-08:00", 
    "_body": "161400", 
    "profile_index": 5, 
    "_head": "7b05", 
    "rate": 0.5, 
    "offset": 39600000, 
    "_date": "00c00b0210"
  }, 
  {
    "_type": "BasalProfileStart", 
    "_description": "BasalProfileStart 2016-03-02T09:58:55 head[2], body[3] op[0x7b]", 
    "timestamp": "2016-03-02T09:58:55-08:00", 
    "_body": "0d1600", 
    "profile_index": 4, 
    "_head": "7b04", 
    "rate": 0.55, 
    "offset": 23400000, 
    "_date": "37fa090210"
  }, 
  {
    "_type": "TempBasalDuration", 
    "_description": "TempBasalDuration 2016-03-02T09:58:55 head[2], body[0] op[0x16]", 
    "timestamp": "2016-03-02T09:58:55-08:00", 
    "_body": "", 
    "_head": "1600", 
    "duration (min)": 0, 
    "_date": "37fa094210"
  }, 
  {
    "_type": "TempBasal", 
    "temp": "absolute", 
    "_description": "TempBasal 2016-03-02T09:58:55 head[2], body[1] op[0x33]", 
    "timestamp": "2016-03-02T09:58:55-08:00", 
    "_body": "00", 
    "_head": "3300", 
    "rate": 0.0, 
    "_date": "37fa094210"
  }, 
  {
    "_type": "BasalProfileStart", 
    "_description": "BasalProfileStart 2016-03-02T09:58:53 head[2], body[3] op[0x7b]", 
    "timestamp": "2016-03-02T09:58:53-08:00", 
    "_body": "0d1600", 
    "profile_index": 4, 
    "_head": "7b04", 
    "rate": 0.55, 
    "offset": 23400000, 
    "_date": "35fa090210"
  }, 
  {
    "_type": "TempBasalDuration", 
    "_description": "TempBasalDuration 2016-03-02T09:58:52 head[2], body[0] op[0x16]", 
    "timestamp": "2016-03-02T09:58:52-08:00", 
    "_body": "", 
    "_head": "1600", 
    "duration (min)": 0, 
    "_date": "34fa094210"
  }, 
  {
    "_type": "TempBasal", 
    "temp": "absolute", 
    "_description": "TempBasal 2016-03-02T09:58:52 head[2], body[1] op[0x33]", 
    "timestamp": "2016-03-02T09:58:52-08:00", 
    "_body": "00", 
    "_head": "3300", 
    "rate": 0.0, 
    "_date": "34fa094210"
  }, 
  {
    "_type": "BasalProfileStart", 
    "_description": "BasalProfileStart 2016-03-02T09:58:51 head[2], body[3] op[0x7b]", 
    "timestamp": "2016-03-02T09:58:51-08:00", 
    "_body": "0d1600", 
    "profile_index": 4, 
    "_head": "7b04", 
    "rate": 0.55, 
    "offset": 23400000, 
    "_date": "33fa090210"
  }, 
  {
    "_type": "TempBasalDuration", 
    "_description": "TempBasalDuration 2016-03-02T09:58:51 head[2], body[0] op[0x16]", 
    "timestamp": "2016-03-02T09:58:51-08:00", 
    "_body": "", 
    "_head": "1600", 
    "duration (min)": 0, 
    "_date": "33fa094210"
  }, 
  {
    "_type": "TempBasal", 
    "temp": "absolute", 
    "_description": "TempBasal 2016-03-02T09:58:51 head[2], body[1] op[0x33]", 
    "timestamp": "2016-03-02T09:58:51-08:00", 
    "_body": "00", 
    "_head": "3300", 
    "rate": 0.0, 
    "_date": "33fa094210"
  }, 
  {
    "_type": "Bolus", 
    "_description": "Bolus 2016-03-02T09:52:57 head[8], body[0] op[0x01]", 
    "timestamp": "2016-03-02T09:52:57-08:00", 
    "_body": "", 
    "appended": [
      {
        "_type": "UnabsorbedInsulinBolus", 
        "_description": "UnabsorbedInsulinBolus unknown head[5], body[0] op[0x5c]", 
        "_body": "", 
        "_head": "5c056ab8c0", 
        "data": [
          {
            "amount": 2.65, 
            "age": 184
          }
        ], 
        "_date": ""
      }
    ], 
    "programmed": 0.85, 
    "duration": 0, 
    "amount": 0.85, 
    "unabsorbed": 0.0, 
    "_head": "0100220022000000", 
    "type": "normal", 
    "_date": "39f4290210"
  }, 
  {
    "_type": "BolusWizard", 
    "bg": 94, 
    "_description": "BolusWizard 2016-03-02T09:52:57 head[2], body[15] op[0x5b]", 
    "timestamp": "2016-03-02T09:52:57-08:00", 
    "_body": "125000aa506ef8002af80000002278", 
    "carb_input": 18, 
    "bg_target_high": 120, 
    "sensitivity": 80, 
    "carb_ratio": 17.0, 
    "food_estimate": 1.05, 
    "unabsorbed_insulin_total": 0.0, 
    "correction_estimate": 51.0, 
    "bg_target_low": 110, 
    "_head": "5b5e", 
    "bolus_estimate": 0.85, 
    "_date": "39f4090210"
  }, 
  {
    "_type": "BGReceived", 
    "_description": "BGReceived 2016-03-02T09:50:56 head[2], body[3] op[0x3f]", 
    "timestamp": "2016-03-02T09:50:56-08:00", 
    "_body": "c23647", 
    "_head": "3f0b", 
    "amount": 94, 
    "link": "c23647", 
    "_date": "38f2c96210"
  }, 
  {
    "_type": "CalBGForPH", 
    "_description": "CalBGForPH 2016-03-02T09:50:56 head[2], body[0] op[0x0a]", 
    "timestamp": "2016-03-02T09:50:56-08:00", 
    "_body": "", 
    "_head": "0a5e", 
    "amount": 94, 
    "_date": "38f2296210"
  }, 
  {
    "_type": "TempBasalDuration", 
    "_description": "TempBasalDuration 2016-03-02T09:47:01 head[2], body[0] op[0x16]", 
    "timestamp": "2016-03-02T09:47:01-08:00", 
    "_body": "", 
    "_head": "1601", 
    "duration (min)": 30, 
    "_date": "01ef094210"
  }, 
  {
    "_type": "TempBasal", 
    "temp": "absolute", 
    "_description": "TempBasal 2016-03-02T09:47:01 head[2], body[1] op[0x33]", 
    "timestamp": "2016-03-02T09:47:01-08:00", 
    "_body": "00", 
    "_head": "3300", 
    "rate": 0.0, 
    "_date": "01ef094210"
  }, 
  {
    "_type": "TempBasalDuration", 
    "_description": "TempBasalDuration 2016-03-02T09:46:58 head[2], body[0] op[0x16]", 
    "timestamp": "2016-03-02T09:46:58-08:00", 
    "_body": "", 
    "_head": "1601", 
    "duration (min)": 30, 
    "_date": "3aee094210"
  }, 
  {
    "_type": "TempBasal", 
    "temp": "absolute", 
    "_description": "TempBasal 2016-03-02T09:46:58 head[2], body[1] op[0x33]", 
    "timestamp": "2016-03-02T09:46:58-08:00", 
    "_body": "00", 
    "_head": "3300", 
    "rate": 0.0, 
    "_date": "3aee094210"
  }, 
  {
    "_type": "TempBasalDuration", 
    "_description": "TempBasalDuration 2016-03-02T09:46:57 head[2], body[0] op[0x16]", 
    "timestamp": "2016-03-02T09:46:57-08:00", 
    "_body": "", 
    "_head": "1601", 
    "duration (min)": 30, 
    "_date": "39ee094210"
  }, 
  {
    "_type": "TempBasal", 
    "temp": "absolute", 
    "_description": "TempBasal 2016-03-02T09:46:57 head[2], body[1] op[0x33]", 
    "timestamp": "2016-03-02T09:46:57-08:00", 
    "_body": "00", 
    "_head": "3300", 
    "rate": 0.0, 
    "_date": "39ee094210"
  }, 
  {
    "_type": "TempBasalDuration", 
    "_description": "TempBasalDuration 2016-03-02T09:41:45 head[2], body[0] op[0x16]", 
    "timestamp": "2016-03-02T09:41:45-08:00", 
    "_body": "", 
    "_head": "1601", 
    "duration (min)": 30, 
    "_date": "2de9094210"
  }, 
  {
    "_type": "TempBasal", 
    "temp": "absolute", 
    "_description": "TempBasal 2016-03-02T09:41:45 head[2], body[1] op[0x33]", 
    "timestamp": "2016-03-02T09:41:45-08:00", 
    "_body": "00", 
    "_head": "3300", 
    "rate": 0.0, 
    "_date": "2de9094210"
  }, 
  {
    "_type": "TempBasalDuration", 
    "_description": "TempBasalDuration 2016-03-02T09:41:42 head[2], body[0] op[0x16]", 
    "timestamp": "2016-03-02T09:41:42-08:00", 
    "_body": "", 
    "_head": "1601", 
    "duration (min)": 30, 
    "_date": "2ae9094210"
  }, 
  {
    "_type": "TempBasal", 
    "temp": "absolute", 
    "_description": "TempBasal 2016-03-02T09:41:42 head[2], body[1] op[0x33]", 
    "timestamp": "2016-03-02T09:41:42-08:00", 
    "_body": "00", 
    "_head": "3300", 
    "rate": 0.0, 
    "_date": "2ae9094210"
  }, 
  {
    "_type": "TempBasalDuration", 
    "_description": "TempBasalDuration 2016-03-02T09:41:41 head[2], body[0] op[0x16]", 
    "timestamp": "2016-03-02T09:41:41-08:00", 
    "_body": "", 
    "_head": "1601", 
    "duration (min)": 30, 
    "_date": "29e9094210"
  }, 
  {
    "_type": "TempBasal", 
    "temp": "absolute", 
    "_description": "TempBasal 2016-03-02T09:41:41 head[2], body[1] op[0x33]", 
    "timestamp": "2016-03-02T09:41:41-08:00", 
    "_body": "00", 
    "_head": "3300", 
    "rate": 0.0, 
    "_date": "29e9094210"
  }, 
  {
    "_type": "TempBasalDuration", 
    "_description": "TempBasalDuration 2016-03-02T09:38:37 head[2], body[0] op[0x16]", 
    "timestamp": "2016-03-02T09:38:37-08:00", 
    "_body": "", 
    "_head": "1601", 
    "duration (min)": 30, 
    "_date": "25e6094210"
  }, 
  {
    "_type": "TempBasal", 
    "temp": "absolute", 
    "_description": "TempBasal 2016-03-02T09:38:37 head[2], body[1] op[0x33]", 
    "timestamp": "2016-03-02T09:38:37-08:00", 
    "_body": "00", 
    "_head": "3300", 
    "rate": 0.0, 
    "_date": "25e6094210"
  }, 
  {
    "_type": "TempBasalDuration", 
    "_description": "TempBasalDuration 2016-03-02T09:38:34 head[2], body[0] op[0x16]", 
    "timestamp": "2016-03-02T09:38:34-08:00", 
    "_body": "", 
    "_head": "1601", 
    "duration (min)": 30, 
    "_date": "22e6094210"
  }, 
  {
    "_type": "TempBasal", 
    "temp": "absolute", 
    "_description": "TempBasal 2016-03-02T09:38:34 head[2], body[1] op[0x33]", 
    "timestamp": "2016-03-02T09:38:34-08:00", 
    "_body": "00", 
    "_head": "3300", 
    "rate": 0.0, 
    "_date": "22e6094210"
  }, 
  {
    "_type": "TempBasalDuration", 
    "_description": "TempBasalDuration 2016-03-02T09:38:33 head[2], body[0] op[0x16]", 
    "timestamp": "2016-03-02T09:38:33-08:00", 
    "_body": "", 
    "_head": "1601", 
    "duration (min)": 30, 
    "_date": "21e6094210"
  }, 
  {
    "_type": "TempBasal", 
    "temp": "absolute", 
    "_description": "TempBasal 2016-03-02T09:38:33 head[2], body[1] op[0x33]", 
    "timestamp": "2016-03-02T09:38:33-08:00", 
    "_body": "00", 
    "_head": "3300", 
    "rate": 0.0, 
    "_date": "21e6094210"
  }, 
  {
    "_type": "TempBasalDuration", 
    "_description": "TempBasalDuration 2016-03-02T09:31:57 head[2], body[0] op[0x16]", 
    "timestamp": "2016-03-02T09:31:57-08:00", 
    "_body": "", 
    "_head": "1601", 
    "duration (min)": 30, 
    "_date": "39df094210"
  }, 
  {
    "_type": "TempBasal", 
    "temp": "absolute", 
    "_description": "TempBasal 2016-03-02T09:31:57 head[2], body[1] op[0x33]", 
    "timestamp": "2016-03-02T09:31:57-08:00", 
    "_body": "00", 
    "_head": "3300", 
    "rate": 0.0, 
    "_date": "39df094210"
  }, 
  {
    "_type": "TempBasalDuration", 
    "_description": "TempBasalDuration 2016-03-02T09:31:54 head[2], body[0] op[0x16]", 
    "timestamp": "2016-03-02T09:31:54-08:00", 
    "_body": "", 
    "_head": "1601", 
    "duration (min)": 30, 
    "_date": "36df094210"
  }, 
  {
    "_type": "TempBasal", 
    "temp": "absolute", 
    "_description": "TempBasal 2016-03-02T09:31:54 head[2], body[1] op[0x33]", 
    "timestamp": "2016-03-02T09:31:54-08:00", 
    "_body": "00", 
    "_head": "3300", 
    "rate": 0.0, 
    "_date": "36df094210"
  }, 
  {
    "_type": "TempBasalDuration", 
    "_description": "TempBasalDuration 2016-03-02T09:31:53 head[2], body[0] op[0x16]", 
    "timestamp": "2016-03-02T09:31:53-08:00", 
    "_body": "", 
    "_head": "1601", 
    "duration (min)": 30, 
    "_date": "35df094210"
  }, 
  {
    "_type": "TempBasal", 
    "temp": "absolute", 
    "_description": "TempBasal 2016-03-02T09:31:53 head[2], body[1] op[0x33]", 
    "timestamp": "2016-03-02T09:31:53-08:00", 
    "_body": "00", 
    "_head": "3300", 
    "rate": 0.0, 
    "_date": "35df094210"
  }, 
  {
    "_type": "TempBasalDuration", 
    "_description": "TempBasalDuration 2016-03-02T09:27:09 head[2], body[0] op[0x16]", 
    "timestamp": "2016-03-02T09:27:09-08:00", 
    "_body": "", 
    "_head": "1601", 
    "duration (min)": 30, 
    "_date": "09db094210"
  }, 
  {
    "_type": "TempBasal", 
    "temp": "absolute", 
    "_description": "TempBasal 2016-03-02T09:27:09 head[2], body[1] op[0x33]", 
    "timestamp": "2016-03-02T09:27:09-08:00", 
    "_body": "00", 
    "_head": "3300", 
    "rate": 0.0, 
    "_date": "09db094210"
  }, 
  {
    "_type": "TempBasalDuration", 
    "_description": "TempBasalDuration 2016-03-02T09:27:07 head[2], body[0] op[0x16]", 
    "timestamp": "2016-03-02T09:27:07-08:00", 
    "_body": "", 
    "_head": "1601", 
    "duration (min)": 30, 
    "_date": "07db094210"
  }, 
  {
    "_type": "TempBasal", 
    "temp": "absolute", 
    "_description": "TempBasal 2016-03-02T09:27:07 head[2], body[1] op[0x33]", 
    "timestamp": "2016-03-02T09:27:07-08:00", 
    "_body": "00", 
    "_head": "3300", 
    "rate": 0.0, 
    "_date": "07db094210"
  }, 
  {
    "_type": "TempBasalDuration", 
    "_description": "TempBasalDuration 2016-03-02T09:27:05 head[2], body[0] op[0x16]", 
    "timestamp": "2016-03-02T09:27:05-08:00", 
    "_body": "", 
    "_head": "1601", 
    "duration (min)": 30, 
    "_date": "05db094210"
  }, 
  {
    "_type": "TempBasal", 
    "temp": "absolute", 
    "_description": "TempBasal 2016-03-02T09:27:05 head[2], body[1] op[0x33]", 
    "timestamp": "2016-03-02T09:27:05-08:00", 
    "_body": "00", 
    "_head": "3300", 
    "rate": 0.0, 
    "_date": "05db094210"
  }, 
  {
    "_type": "Prime", 
    "_description": "Prime 2016-03-02T09:09:55 head[5], body[0] op[0x03]", 
    "timestamp": "2016-03-02T09:09:55-08:00", 
    "_body": "", 
    "_head": "0300070007", 
    "amount": 0.7, 
    "fixed": 0.7, 
    "type": "fixed", 
    "_date": "37c9090210"
  }, 
  {
    "_type": "TempBasalDuration", 
    "_description": "TempBasalDuration 2016-03-02T09:06:46 head[2], body[0] op[0x16]", 
    "timestamp": "2016-03-02T09:06:46-08:00", 
    "_body": "", 
    "_head": "1601", 
    "duration (min)": 30, 
    "_date": "2ec6094210"
  }, 
  {
    "_type": "TempBasal", 
    "temp": "absolute", 
    "_description": "TempBasal 2016-03-02T09:06:46 head[2], body[1] op[0x33]", 
    "timestamp": "2016-03-02T09:06:46-08:00", 
    "_body": "00", 
    "_head": "3300", 
    "rate": 0.0, 
    "_date": "2ec6094210"
  }, 
  {
    "_type": "TempBasalDuration", 
    "_description": "TempBasalDuration 2016-03-02T09:06:43 head[2], body[0] op[0x16]", 
    "timestamp": "2016-03-02T09:06:43-08:00", 
    "_body": "", 
    "_head": "1601", 
    "duration (min)": 30, 
    "_date": "2bc6094210"
  }, 
  {
    "_type": "TempBasal", 
    "temp": "absolute", 
    "_description": "TempBasal 2016-03-02T09:06:43 head[2], body[1] op[0x33]", 
    "timestamp": "2016-03-02T09:06:43-08:00", 
    "_body": "00", 
    "_head": "3300", 
    "rate": 0.0, 
    "_date": "2bc6094210"
  }, 
  {
    "_type": "TempBasalDuration", 
    "_description": "TempBasalDuration 2016-03-02T09:06:42 head[2], body[0] op[0x16]", 
    "timestamp": "2016-03-02T09:06:42-08:00", 
    "_body": "", 
    "_head": "1601", 
    "duration (min)": 30, 
    "_date": "2ac6094210"
  }, 
  {
    "_type": "TempBasal", 
    "temp": "absolute", 
    "_description": "TempBasal 2016-03-02T09:06:42 head[2], body[1] op[0x33]", 
    "timestamp": "2016-03-02T09:06:42-08:00", 
    "_body": "00", 
    "_head": "3300", 
    "rate": 0.0, 
    "_date": "2ac6094210"
  }, 
  {
    "_type": "TempBasalDuration", 
    "_description": "TempBasalDuration 2016-03-02T09:03:19 head[2], body[0] op[0x16]", 
    "timestamp": "2016-03-02T09:03:19-08:00", 
    "_body": "", 
    "_head": "1601", 
    "duration (min)": 30, 
    "_date": "13c3094210"
  }, 
  {
    "_type": "TempBasal", 
    "temp": "absolute", 
    "_description": "TempBasal 2016-03-02T09:03:19 head[2], body[1] op[0x33]", 
    "timestamp": "2016-03-02T09:03:19-08:00", 
    "_body": "00", 
    "_head": "3300", 
    "rate": 0.0, 
    "_date": "13c3094210"
  }, 
  {
    "_type": "TempBasalDuration", 
    "_description": "TempBasalDuration 2016-03-02T09:03:16 head[2], body[0] op[0x16]", 
    "timestamp": "2016-03-02T09:03:16-08:00", 
    "_body": "", 
    "_head": "1601", 
    "duration (min)": 30, 
    "_date": "10c3094210"
  }, 
  {
    "_type": "TempBasal", 
    "temp": "absolute", 
    "_description": "TempBasal 2016-03-02T09:03:16 head[2], body[1] op[0x33]", 
    "timestamp": "2016-03-02T09:03:16-08:00", 
    "_body": "00", 
    "_head": "3300", 
    "rate": 0.0, 
    "_date": "10c3094210"
  }, 
  {
    "_type": "BasalProfileStart", 
    "_description": "BasalProfileStart 2016-03-02T08:52:37 head[2], body[3] op[0x7b]", 
    "timestamp": "2016-03-02T08:52:37-08:00", 
    "_body": "0d1600", 
    "profile_index": 4, 
    "_head": "7b04", 
    "rate": 0.55, 
    "offset": 23400000, 
    "_date": "25f4080210"
  }, 
  {
    "_type": "TempBasalDuration", 
    "_description": "TempBasalDuration 2016-03-02T08:22:37 head[2], body[0] op[0x16]", 
    "timestamp": "2016-03-02T08:22:37-08:00", 
    "_body": "", 
    "_head": "1601", 
    "duration (min)": 30, 
    "_date": "25d6084210"
  }, 
  {
    "_type": "TempBasal", 
    "temp": "absolute", 
    "_description": "TempBasal 2016-03-02T08:22:37 head[2], body[1] op[0x33]", 
    "timestamp": "2016-03-02T08:22:37-08:00", 
    "_body": "00", 
    "_head": "3350", 
    "rate": 2.0, 
    "_date": "25d6084210"
  }, 
  {
    "_type": "TempBasalDuration", 
    "_description": "TempBasalDuration 2016-03-02T08:22:34 head[2], body[0] op[0x16]", 
    "timestamp": "2016-03-02T08:22:34-08:00", 
    "_body": "", 
    "_head": "1601", 
    "duration (min)": 30, 
    "_date": "22d6084210"
  }, 
  {
    "_type": "TempBasal", 
    "temp": "absolute", 
    "_description": "TempBasal 2016-03-02T08:22:34 head[2], body[1] op[0x33]", 
    "timestamp": "2016-03-02T08:22:34-08:00", 
    "_body": "00", 
    "_head": "3350", 
    "rate": 2.0, 
    "_date": "22d6084210"
  }, 
  {
    "_type": "TempBasalDuration", 
    "_description": "TempBasalDuration 2016-03-02T08:22:33 head[2], body[0] op[0x16]", 
    "timestamp": "2016-03-02T08:22:33-08:00", 
    "_body": "", 
    "_head": "1601", 
    "duration (min)": 30, 
    "_date": "21d6084210"
  }, 
  {
    "_type": "TempBasal", 
    "temp": "absolute", 
    "_description": "TempBasal 2016-03-02T08:22:33 head[2], body[1] op[0x33]", 
    "timestamp": "2016-03-02T08:22:33-08:00", 
    "_body": "00", 
    "_head": "3350", 
    "rate": 2.0, 
    "_date": "21d6084210"
  }, 
  {
    "_type": "TempBasalDuration", 
    "_description": "TempBasalDuration 2016-03-02T08:17:16 head[2], body[0] op[0x16]", 
    "timestamp": "2016-03-02T08:17:16-08:00", 
    "_body": "", 
    "_head": "1601", 
    "duration (min)": 30, 
    "_date": "10d1084210"
  }, 
  {
    "_type": "TempBasal", 
    "temp": "absolute", 
    "_description": "TempBasal 2016-03-02T08:17:16 head[2], body[1] op[0x33]", 
    "timestamp": "2016-03-02T08:17:16-08:00", 
    "_body": "00", 
    "_head": "3348", 
    "rate": 1.8, 
    "_date": "10d1084210"
  }, 
  {
    "_type": "TempBasalDuration", 
    "_description": "TempBasalDuration 2016-03-02T08:17:13 head[2], body[0] op[0x16]", 
    "timestamp": "2016-03-02T08:17:13-08:00", 
    "_body": "", 
    "_head": "1601", 
    "duration (min)": 30, 
    "_date": "0dd1084210"
  }, 
  {
    "_type": "TempBasal", 
    "temp": "absolute", 
    "_description": "TempBasal 2016-03-02T08:17:13 head[2], body[1] op[0x33]", 
    "timestamp": "2016-03-02T08:17:13-08:00", 
    "_body": "00", 
    "_head": "3348", 
    "rate": 1.8, 
    "_date": "0dd1084210"
  }, 
  {
    "_type": "TempBasalDuration", 
    "_description": "TempBasalDuration 2016-03-02T08:17:12 head[2], body[0] op[0x16]", 
    "timestamp": "2016-03-02T08:17:12-08:00", 
    "_body": "", 
    "_head": "1601", 
    "duration (min)": 30, 
    "_date": "0cd1084210"
  }, 
  {
    "_type": "TempBasal", 
    "temp": "absolute", 
    "_description": "TempBasal 2016-03-02T08:17:12 head[2], body[1] op[0x33]", 
    "timestamp": "2016-03-02T08:17:12-08:00", 
    "_body": "00", 
    "_head": "3348", 
    "rate": 1.8, 
    "_date": "0cd1084210"
  }, 
  {
    "_type": "TempBasalDuration", 
    "_description": "TempBasalDuration 2016-03-02T08:12:25 head[2], body[0] op[0x16]", 
    "timestamp": "2016-03-02T08:12:25-08:00", 
    "_body": "", 
    "_head": "1601", 
    "duration (min)": 30, 
    "_date": "19cc084210"
  }, 
  {
    "_type": "TempBasal", 
    "temp": "absolute", 
    "_description": "TempBasal 2016-03-02T08:12:25 head[2], body[1] op[0x33]", 
    "timestamp": "2016-03-02T08:12:25-08:00", 
    "_body": "00", 
    "_head": "3341", 
    "rate": 1.625, 
    "_date": "19cc084210"
  }, 
  {
    "_type": "TempBasalDuration", 
    "_description": "TempBasalDuration 2016-03-02T08:12:22 head[2], body[0] op[0x16]", 
    "timestamp": "2016-03-02T08:12:22-08:00", 
    "_body": "", 
    "_head": "1601", 
    "duration (min)": 30, 
    "_date": "16cc084210"
  }, 
  {
    "_type": "TempBasal", 
    "temp": "absolute", 
    "_description": "TempBasal 2016-03-02T08:12:22 head[2], body[1] op[0x33]", 
    "timestamp": "2016-03-02T08:12:22-08:00", 
    "_body": "00", 
    "_head": "3341", 
    "rate": 1.625, 
    "_date": "16cc084210"
  }, 
  {
    "_type": "TempBasalDuration", 
    "_description": "TempBasalDuration 2016-03-02T08:12:21 head[2], body[0] op[0x16]", 
    "timestamp": "2016-03-02T08:12:21-08:00", 
    "_body": "", 
    "_head": "1601", 
    "duration (min)": 30, 
    "_date": "15cc084210"
  }, 
  {
    "_type": "TempBasal", 
    "temp": "absolute", 
    "_description": "TempBasal 2016-03-02T08:12:21 head[2], body[1] op[0x33]", 
    "timestamp": "2016-03-02T08:12:21-08:00", 
    "_body": "00", 
    "_head": "3341", 
    "rate": 1.625, 
    "_date": "15cc084210"
  }, 
  {
    "_type": "TempBasalDuration", 
    "_description": "TempBasalDuration 2016-03-02T08:07:08 head[2], body[0] op[0x16]", 
    "timestamp": "2016-03-02T08:07:08-08:00", 
    "_body": "", 
    "_head": "1601", 
    "duration (min)": 30, 
    "_date": "08c7084210"
  }, 
  {
    "_type": "TempBasal", 
    "temp": "absolute", 
    "_description": "TempBasal 2016-03-02T08:07:08 head[2], body[1] op[0x33]", 
    "timestamp": "2016-03-02T08:07:08-08:00", 
    "_body": "00", 
    "_head": "3337", 
    "rate": 1.375, 
    "_date": "08c7084210"
  }, 
  {
    "_type": "TempBasalDuration", 
    "_description": "TempBasalDuration 2016-03-02T08:07:05 head[2], body[0] op[0x16]", 
    "timestamp": "2016-03-02T08:07:05-08:00", 
    "_body": "", 
    "_head": "1601", 
    "duration (min)": 30, 
    "_date": "05c7084210"
  }, 
  {
    "_type": "TempBasal", 
    "temp": "absolute", 
    "_description": "TempBasal 2016-03-02T08:07:05 head[2], body[1] op[0x33]", 
    "timestamp": "2016-03-02T08:07:05-08:00", 
    "_body": "00", 
    "_head": "3337", 
    "rate": 1.375, 
    "_date": "05c7084210"
  }, 
  {
    "_type": "TempBasalDuration", 
    "_description": "TempBasalDuration 2016-03-02T08:07:04 head[2], body[0] op[0x16]", 
    "timestamp": "2016-03-02T08:07:04-08:00", 
    "_body": "", 
    "_head": "1601", 
    "duration (min)": 30, 
    "_date": "04c7084210"
  }, 
  {
    "_type": "TempBasal", 
    "temp": "absolute", 
    "_description": "TempBasal 2016-03-02T08:07:04 head[2], body[1] op[0x33]", 
    "timestamp": "2016-03-02T08:07:04-08:00", 
    "_body": "00", 
    "_head": "3337", 
    "rate": 1.375, 
    "_date": "04c7084210"
  }, 
  {
    "_type": "TempBasalDuration", 
    "_description": "TempBasalDuration 2016-03-02T08:02:10 head[2], body[0] op[0x16]", 
    "timestamp": "2016-03-02T08:02:10-08:00", 
    "_body": "", 
    "_head": "1601", 
    "duration (min)": 30, 
    "_date": "0ac2084210"
  }, 
  {
    "_type": "TempBasal", 
    "temp": "absolute", 
    "_description": "TempBasal 2016-03-02T08:02:10 head[2], body[1] op[0x33]", 
    "timestamp": "2016-03-02T08:02:10-08:00", 
    "_body": "00", 
    "_head": "3332", 
    "rate": 1.25, 
    "_date": "0ac2084210"
  }, 
  {
    "_type": "TempBasalDuration", 
    "_description": "TempBasalDuration 2016-03-02T08:02:07 head[2], body[0] op[0x16]", 
    "timestamp": "2016-03-02T08:02:07-08:00", 
    "_body": "", 
    "_head": "1601", 
    "duration (min)": 30, 
    "_date": "07c2084210"
  }, 
  {
    "_type": "TempBasal", 
    "temp": "absolute", 
    "_description": "TempBasal 2016-03-02T08:02:07 head[2], body[1] op[0x33]", 
    "timestamp": "2016-03-02T08:02:07-08:00", 
    "_body": "00", 
    "_head": "3332", 
    "rate": 1.25, 
    "_date": "07c2084210"
  }, 
  {
    "_type": "TempBasalDuration", 
    "_description": "TempBasalDuration 2016-03-02T08:02:06 head[2], body[0] op[0x16]", 
    "timestamp": "2016-03-02T08:02:06-08:00", 
    "_body": "", 
    "_head": "1601", 
    "duration (min)": 30, 
    "_date": "06c2084210"
  }, 
  {
    "_type": "TempBasal", 
    "temp": "absolute", 
    "_description": "TempBasal 2016-03-02T08:02:06 head[2], body[1] op[0x33]", 
    "timestamp": "2016-03-02T08:02:06-08:00", 
    "_body": "00", 
    "_head": "3332", 
    "rate": 1.25, 
    "_date": "06c2084210"
  }, 
  {
    "_type": "BasalProfileStart", 
    "_description": "BasalProfileStart 2016-03-02T07:42:49 head[2], body[3] op[0x7b]", 
    "timestamp": "2016-03-02T07:42:49-08:00", 
    "_body": "0d1600", 
    "profile_index": 4, 
    "_head": "7b04", 
    "rate": 0.55, 
    "offset": 23400000, 
    "_date": "31ea070210"
  }, 
  {
    "_type": "TempBasalDuration", 
    "_description": "TempBasalDuration 2016-03-02T07:42:49 head[2], body[0] op[0x16]", 
    "timestamp": "2016-03-02T07:42:49-08:00", 
    "_body": "", 
    "_head": "1600", 
    "duration (min)": 0, 
    "_date": "31ea074210"
  }, 
  {
    "_type": "TempBasal", 
    "temp": "absolute", 
    "_description": "TempBasal 2016-03-02T07:42:49 head[2], body[1] op[0x33]", 
    "timestamp": "2016-03-02T07:42:49-08:00", 
    "_body": "00", 
    "_head": "3300", 
    "rate": 0.0, 
    "_date": "31ea074210"
  }, 
  {
    "_type": "BasalProfileStart", 
    "_description": "BasalProfileStart 2016-03-02T07:42:47 head[2], body[3] op[0x7b]", 
    "timestamp": "2016-03-02T07:42:47-08:00", 
    "_body": "0d1600", 
    "profile_index": 4, 
    "_head": "7b04", 
    "rate": 0.55, 
    "offset": 23400000, 
    "_date": "2fea070210"
  }, 
  {
    "_type": "TempBasalDuration", 
    "_description": "TempBasalDuration 2016-03-02T07:42:47 head[2], body[0] op[0x16]", 
    "timestamp": "2016-03-02T07:42:47-08:00", 
    "_body": "", 
    "_head": "1600", 
    "duration (min)": 0, 
    "_date": "2fea074210"
  }, 
  {
    "_type": "TempBasal", 
    "temp": "absolute", 
    "_description": "TempBasal 2016-03-02T07:42:47 head[2], body[1] op[0x33]", 
    "timestamp": "2016-03-02T07:42:47-08:00", 
    "_body": "00", 
    "_head": "3300", 
    "rate": 0.0, 
    "_date": "2fea074210"
  }, 
  {
    "_type": "BasalProfileStart", 
    "_description": "BasalProfileStart 2016-03-02T07:42:45 head[2], body[3] op[0x7b]", 
    "timestamp": "2016-03-02T07:42:45-08:00", 
    "_body": "0d1600", 
    "profile_index": 4, 
    "_head": "7b04", 
    "rate": 0.55, 
    "offset": 23400000, 
    "_date": "2dea070210"
  }, 
  {
    "_type": "TempBasalDuration", 
    "_description": "TempBasalDuration 2016-03-02T07:42:45 head[2], body[0] op[0x16]", 
    "timestamp": "2016-03-02T07:42:45-08:00", 
    "_body": "", 
    "_head": "1600", 
    "duration (min)": 0, 
    "_date": "2dea074210"
  }, 
  {
    "_type": "TempBasal", 
    "temp": "absolute", 
    "_description": "TempBasal 2016-03-02T07:42:45 head[2], body[1] op[0x33]", 
    "timestamp": "2016-03-02T07:42:45-08:00", 
    "_body": "00", 
    "_head": "3300", 
    "rate": 0.0, 
    "_date": "2dea074210"
  }, 
  {
    "_type": "TempBasalDuration", 
    "_description": "TempBasalDuration 2016-03-02T07:31:43 head[2], body[0] op[0x16]", 
    "timestamp": "2016-03-02T07:31:43-08:00", 
    "_body": "", 
    "_head": "1601", 
    "duration (min)": 30, 
    "_date": "2bdf074210"
  }, 
  {
    "_type": "TempBasal", 
    "temp": "absolute", 
    "_description": "TempBasal 2016-03-02T07:31:43 head[2], body[1] op[0x33]", 
    "timestamp": "2016-03-02T07:31:43-08:00", 
    "_body": "00", 
    "_head": "3300", 
    "rate": 0.0, 
    "_date": "2bdf074210"
  }, 
  {
    "_type": "TempBasalDuration", 
    "_description": "TempBasalDuration 2016-03-02T07:31:41 head[2], body[0] op[0x16]", 
    "timestamp": "2016-03-02T07:31:41-08:00", 
    "_body": "", 
    "_head": "1601", 
    "duration (min)": 30, 
    "_date": "29df074210"
  }, 
  {
    "_type": "TempBasal", 
    "temp": "absolute", 
    "_description": "TempBasal 2016-03-02T07:31:41 head[2], body[1] op[0x33]", 
    "timestamp": "2016-03-02T07:31:41-08:00", 
    "_body": "00", 
    "_head": "3300", 
    "rate": 0.0, 
    "_date": "29df074210"
  }, 
  {
    "_type": "TempBasalDuration", 
    "_description": "TempBasalDuration 2016-03-02T07:31:39 head[2], body[0] op[0x16]", 
    "timestamp": "2016-03-02T07:31:39-08:00", 
    "_body": "", 
    "_head": "1601", 
    "duration (min)": 30, 
    "_date": "27df074210"
  }, 
  {
    "_type": "TempBasal", 
    "temp": "absolute", 
    "_description": "TempBasal 2016-03-02T07:31:39 head[2], body[1] op[0x33]", 
    "timestamp": "2016-03-02T07:31:39-08:00", 
    "_body": "00", 
    "_head": "3300", 
    "rate": 0.0, 
    "_date": "27df074210"
  }, 
  {
    "_type": "TempBasalDuration", 
    "_description": "TempBasalDuration 2016-03-02T07:28:43 head[2], body[0] op[0x16]", 
    "timestamp": "2016-03-02T07:28:43-08:00", 
    "_body": "", 
    "_head": "1601", 
    "duration (min)": 30, 
    "_date": "2bdc074210"
  }, 
  {
    "_type": "TempBasal", 
    "temp": "absolute", 
    "_description": "TempBasal 2016-03-02T07:28:43 head[2], body[1] op[0x33]", 
    "timestamp": "2016-03-02T07:28:43-08:00", 
    "_body": "00", 
    "_head": "3300", 
    "rate": 0.0, 
    "_date": "2bdc074210"
  }, 
  {
    "_type": "TempBasalDuration", 
    "_description": "TempBasalDuration 2016-03-02T07:28:41 head[2], body[0] op[0x16]", 
    "timestamp": "2016-03-02T07:28:41-08:00", 
    "_body": "", 
    "_head": "1601", 
    "duration (min)": 30, 
    "_date": "29dc074210"
  }, 
  {
    "_type": "TempBasal", 
    "temp": "absolute", 
    "_description": "TempBasal 2016-03-02T07:28:41 head[2], body[1] op[0x33]", 
    "timestamp": "2016-03-02T07:28:41-08:00", 
    "_body": "00", 
    "_head": "3300", 
    "rate": 0.0, 
    "_date": "29dc074210"
  }, 
  {
    "_type": "TempBasalDuration", 
    "_description": "TempBasalDuration 2016-03-02T07:28:39 head[2], body[0] op[0x16]", 
    "timestamp": "2016-03-02T07:28:39-08:00", 
    "_body": "", 
    "_head": "1601", 
    "duration (min)": 30, 
    "_date": "27dc074210"
  }, 
  {
    "_type": "TempBasal", 
    "temp": "absolute", 
    "_description": "TempBasal 2016-03-02T07:28:39 head[2], body[1] op[0x33]", 
    "timestamp": "2016-03-02T07:28:39-08:00", 
    "_body": "00", 
    "_head": "3300", 
    "rate": 0.0, 
    "_date": "27dc074210"
  }, 
  {
    "programmed": 2.65, 
    "_type": "Bolus", 
    "_description": "Bolus 2016-03-02T06:55:26 head[8], body[0] op[0x01]", 
    "timestamp": "2016-03-02T06:55:26-08:00", 
    "_body": "", 
    "_head": "01006a006a000000", 
    "amount": 2.65, 
    "unabsorbed": 0.0, 
    "duration": 0, 
    "type": "normal", 
    "_date": "1af7260210"
  }, 
  {
    "_type": "BolusWizard", 
    "bg": 142, 
    "_description": "BolusWizard 2016-03-02T06:55:26 head[2], body[15] op[0x5b]", 
    "timestamp": "2016-03-02T06:55:26-08:00", 
    "_body": "18500064506e0a0060000000006a78", 
    "carb_input": 24, 
    "bg_target_high": 120, 
    "sensitivity": 80, 
    "carb_ratio": 10.0, 
    "food_estimate": 2.4, 
    "unabsorbed_insulin_total": 0.0, 
    "correction_estimate": 0.25, 
    "bg_target_low": 110, 
    "_head": "5b8e", 
    "bolus_estimate": 2.65, 
    "_date": "1af7060210"
  }, 
  {
    "_type": "BGReceived", 
    "_description": "BGReceived 2016-03-02T06:54:48 head[2], body[3] op[0x3f]", 
    "timestamp": "2016-03-02T06:54:48-08:00", 
    "_body": "c23647", 
    "_head": "3f11", 
    "amount": 142, 
    "link": "c23647", 
    "_date": "30f6c66210"
  }, 
  {
    "_type": "CalBGForPH", 
    "_description": "CalBGForPH 2016-03-02T06:54:48 head[2], body[0] op[0x0a]", 
    "timestamp": "2016-03-02T06:54:48-08:00", 
    "_body": "", 
    "_head": "0a8e", 
    "amount": 142, 
    "_date": "30f6266210"
  }, 
  {
    "_type": "BasalProfileStart", 
    "_description": "BasalProfileStart 2016-03-02T06:47:03 head[2], body[3] op[0x7b]", 
    "timestamp": "2016-03-02T06:47:03-08:00", 
    "_body": "0d1600", 
    "profile_index": 4, 
    "_head": "7b04", 
    "rate": 0.55, 
    "offset": 23400000, 
    "_date": "03ef060210"
  }, 
  {
    "_type": "TempBasalDuration", 
    "_description": "TempBasalDuration 2016-03-02T06:47:03 head[2], body[0] op[0x16]", 
    "timestamp": "2016-03-02T06:47:03-08:00", 
    "_body": "", 
    "_head": "1600", 
    "duration (min)": 0, 
    "_date": "03ef064210"
  }, 
  {
    "_type": "TempBasal", 
    "temp": "absolute", 
    "_description": "TempBasal 2016-03-02T06:47:03 head[2], body[1] op[0x33]", 
    "timestamp": "2016-03-02T06:47:03-08:00", 
    "_body": "00", 
    "_head": "3300", 
    "rate": 0.0, 
    "_date": "03ef064210"
  }, 
  {
    "_type": "BasalProfileStart", 
    "_description": "BasalProfileStart 2016-03-02T06:47:00 head[2], body[3] op[0x7b]", 
    "timestamp": "2016-03-02T06:47:00-08:00", 
    "_body": "0d1600", 
    "profile_index": 4, 
    "_head": "7b04", 
    "rate": 0.55, 
    "offset": 23400000, 
    "_date": "00ef060210"
  }, 
  {
    "_type": "TempBasalDuration", 
    "_description": "TempBasalDuration 2016-03-02T06:47:00 head[2], body[0] op[0x16]", 
    "timestamp": "2016-03-02T06:47:00-08:00", 
    "_body": "", 
    "_head": "1600", 
    "duration (min)": 0, 
    "_date": "00ef064210"
  }, 
  {
    "_type": "TempBasal", 
    "temp": "absolute", 
    "_description": "TempBasal 2016-03-02T06:47:00 head[2], body[1] op[0x33]", 
    "timestamp": "2016-03-02T06:47:00-08:00", 
    "_body": "00", 
    "_head": "3300", 
    "rate": 0.0, 
    "_date": "00ef064210"
  }, 
  {
    "_type": "BasalProfileStart", 
    "_description": "BasalProfileStart 2016-03-02T06:46:59 head[2], body[3] op[0x7b]", 
    "timestamp": "2016-03-02T06:46:59-08:00", 
    "_body": "0d1600", 
    "profile_index": 4, 
    "_head": "7b04", 
    "rate": 0.55, 
    "offset": 23400000, 
    "_date": "3bee060210"
  }, 
  {
    "_type": "TempBasalDuration", 
    "_description": "TempBasalDuration 2016-03-02T06:46:59 head[2], body[0] op[0x16]", 
    "timestamp": "2016-03-02T06:46:59-08:00", 
    "_body": "", 
    "_head": "1600", 
    "duration (min)": 0, 
    "_date": "3bee064210"
  }, 
  {
    "_type": "TempBasal", 
    "temp": "absolute", 
    "_description": "TempBasal 2016-03-02T06:46:59 head[2], body[1] op[0x33]", 
    "timestamp": "2016-03-02T06:46:59-08:00", 
    "_body": "00", 
    "_head": "3300", 
    "rate": 0.0, 
    "_date": "3bee064210"
  }, 
  {
    "_type": "TempBasalDuration", 
    "_description": "TempBasalDuration 2016-03-02T06:37:38 head[2], body[0] op[0x16]", 
    "timestamp": "2016-03-02T06:37:38-08:00", 
    "_body": "", 
    "_head": "1601", 
    "duration (min)": 30, 
    "_date": "26e5064210"
  }, 
  {
    "_type": "TempBasal", 
    "temp": "absolute", 
    "_description": "TempBasal 2016-03-02T06:37:38 head[2], body[1] op[0x33]", 
    "timestamp": "2016-03-02T06:37:38-08:00", 
    "_body": "00", 
    "_head": "3334", 
    "rate": 1.3, 
    "_date": "26e5064210"
  }, 
  {
    "_type": "TempBasalDuration", 
    "_description": "TempBasalDuration 2016-03-02T06:37:36 head[2], body[0] op[0x16]", 
    "timestamp": "2016-03-02T06:37:36-08:00", 
    "_body": "", 
    "_head": "1601", 
    "duration (min)": 30, 
    "_date": "24e5064210"
  }, 
  {
    "_type": "TempBasal", 
    "temp": "absolute", 
    "_description": "TempBasal 2016-03-02T06:37:36 head[2], body[1] op[0x33]", 
    "timestamp": "2016-03-02T06:37:36-08:00", 
    "_body": "00", 
    "_head": "3334", 
    "rate": 1.3, 
    "_date": "24e5064210"
  }, 
  {
    "_type": "TempBasalDuration", 
    "_description": "TempBasalDuration 2016-03-02T06:37:35 head[2], body[0] op[0x16]", 
    "timestamp": "2016-03-02T06:37:35-08:00", 
    "_body": "", 
    "_head": "1601", 
    "duration (min)": 30, 
    "_date": "23e5064210"
  }, 
  {
    "_type": "TempBasal", 
    "temp": "absolute", 
    "_description": "TempBasal 2016-03-02T06:37:35 head[2], body[1] op[0x33]", 
    "timestamp": "2016-03-02T06:37:35-08:00", 
    "_body": "00", 
    "_head": "3334", 
    "rate": 1.3, 
    "_date": "23e5064210"
  }, 
  {
    "_type": "BasalProfileStart", 
    "_description": "BasalProfileStart 2016-03-02T06:31:47 head[2], body[3] op[0x7b]", 
    "timestamp": "2016-03-02T06:31:47-08:00", 
    "_body": "0d1600", 
    "profile_index": 4, 
    "_head": "7b04", 
    "rate": 0.55, 
    "offset": 23400000, 
    "_date": "2fdf060210"
  }, 
  {
    "_type": "TempBasalDuration", 
    "_description": "TempBasalDuration 2016-03-02T06:31:47 head[2], body[0] op[0x16]", 
    "timestamp": "2016-03-02T06:31:47-08:00", 
    "_body": "", 
    "_head": "1600", 
    "duration (min)": 0, 
    "_date": "2fdf064210"
  }, 
  {
    "_type": "TempBasal", 
    "temp": "absolute", 
    "_description": "TempBasal 2016-03-02T06:31:47 head[2], body[1] op[0x33]", 
    "timestamp": "2016-03-02T06:31:47-08:00", 
    "_body": "00", 
    "_head": "3300", 
    "rate": 0.0, 
    "_date": "2fdf064210"
  }, 
  {
    "_type": "BasalProfileStart", 
    "_description": "BasalProfileStart 2016-03-02T06:31:44 head[2], body[3] op[0x7b]", 
    "timestamp": "2016-03-02T06:31:44-08:00", 
    "_body": "0d1600", 
    "profile_index": 4, 
    "_head": "7b04", 
    "rate": 0.55, 
    "offset": 23400000, 
    "_date": "2cdf060210"
  }, 
  {
    "_type": "TempBasalDuration", 
    "_description": "TempBasalDuration 2016-03-02T06:31:44 head[2], body[0] op[0x16]", 
    "timestamp": "2016-03-02T06:31:44-08:00", 
    "_body": "", 
    "_head": "1600", 
    "duration (min)": 0, 
    "_date": "2cdf064210"
  }, 
  {
    "_type": "TempBasal", 
    "temp": "absolute", 
    "_description": "TempBasal 2016-03-02T06:31:44 head[2], body[1] op[0x33]", 
    "timestamp": "2016-03-02T06:31:44-08:00", 
    "_body": "00", 
    "_head": "3300", 
    "rate": 0.0, 
    "_date": "2cdf064210"
  }, 
  {
    "_type": "BasalProfileStart", 
    "_description": "BasalProfileStart 2016-03-02T06:31:43 head[2], body[3] op[0x7b]", 
    "timestamp": "2016-03-02T06:31:43-08:00", 
    "_body": "0d1600", 
    "profile_index": 4, 
    "_head": "7b04", 
    "rate": 0.55, 
    "offset": 23400000, 
    "_date": "2bdf060210"
  }, 
  {
    "_type": "TempBasalDuration", 
    "_description": "TempBasalDuration 2016-03-02T06:31:43 head[2], body[0] op[0x16]", 
    "timestamp": "2016-03-02T06:31:43-08:00", 
    "_body": "", 
    "_head": "1600", 
    "duration (min)": 0, 
    "_date": "2bdf064210"
  }, 
  {
    "_type": "TempBasal", 
    "temp": "absolute", 
    "_description": "TempBasal 2016-03-02T06:31:43 head[2], body[1] op[0x33]", 
    "timestamp": "2016-03-02T06:31:43-08:00", 
    "_body": "00", 
    "_head": "3300", 
    "rate": 0.0, 
    "_date": "2bdf064210"
  }, 
  {
    "_type": "TempBasalDuration", 
    "_description": "TempBasalDuration 2016-03-02T06:27:08 head[2], body[0] op[0x16]", 
    "timestamp": "2016-03-02T06:27:08-08:00", 
    "_body": "", 
    "_head": "1601", 
    "duration (min)": 30, 
    "_date": "08db064210"
  }, 
  {
    "_type": "TempBasal", 
    "temp": "absolute", 
    "_description": "TempBasal 2016-03-02T06:27:08 head[2], body[1] op[0x33]", 
    "timestamp": "2016-03-02T06:27:08-08:00", 
    "_body": "00", 
    "_head": "3316", 
    "rate": 0.55, 
    "_date": "08db064210"
  }, 
  {
    "_type": "TempBasalDuration", 
    "_description": "TempBasalDuration 2016-03-02T06:27:05 head[2], body[0] op[0x16]", 
    "timestamp": "2016-03-02T06:27:05-08:00", 
    "_body": "", 
    "_head": "1601", 
    "duration (min)": 30, 
    "_date": "05db064210"
  }, 
  {
    "_type": "TempBasal", 
    "temp": "absolute", 
    "_description": "TempBasal 2016-03-02T06:27:05 head[2], body[1] op[0x33]", 
    "timestamp": "2016-03-02T06:27:05-08:00", 
    "_body": "00", 
    "_head": "3316", 
    "rate": 0.55, 
    "_date": "05db064210"
  }, 
  {
    "_type": "TempBasalDuration", 
    "_description": "TempBasalDuration 2016-03-02T06:27:04 head[2], body[0] op[0x16]", 
    "timestamp": "2016-03-02T06:27:04-08:00", 
    "_body": "", 
    "_head": "1601", 
    "duration (min)": 30, 
    "_date": "04db064210"
  }, 
  {
    "_type": "TempBasal", 
    "temp": "absolute", 
    "_description": "TempBasal 2016-03-02T06:27:04 head[2], body[1] op[0x33]", 
    "timestamp": "2016-03-02T06:27:04-08:00", 
    "_body": "00", 
    "_head": "3316", 
    "rate": 0.55, 
    "_date": "04db064210"
  }, 
  {
    "_type": "BasalProfileStart", 
    "_description": "BasalProfileStart 2016-03-02T06:22:27 head[2], body[3] op[0x7b]", 
    "timestamp": "2016-03-02T06:22:27-08:00", 
    "_body": "091000", 
    "profile_index": 3, 
    "_head": "7b03", 
    "rate": 0.4, 
    "offset": 16200000, 
    "_date": "1bd6060210"
  }, 
  {
    "_type": "TempBasalDuration", 
    "_description": "TempBasalDuration 2016-03-02T06:22:27 head[2], body[0] op[0x16]", 
    "timestamp": "2016-03-02T06:22:27-08:00", 
    "_body": "", 
    "_head": "1600", 
    "duration (min)": 0, 
    "_date": "1bd6064210"
  }, 
  {
    "_type": "TempBasal", 
    "temp": "absolute", 
    "_description": "TempBasal 2016-03-02T06:22:27 head[2], body[1] op[0x33]", 
    "timestamp": "2016-03-02T06:22:27-08:00", 
    "_body": "00", 
    "_head": "3300", 
    "rate": 0.0, 
    "_date": "1bd6064210"
  }, 
  {
    "_type": "BasalProfileStart", 
    "_description": "BasalProfileStart 2016-03-02T06:22:25 head[2], body[3] op[0x7b]", 
    "timestamp": "2016-03-02T06:22:25-08:00", 
    "_body": "091000", 
    "profile_index": 3, 
    "_head": "7b03", 
    "rate": 0.4, 
    "offset": 16200000, 
    "_date": "19d6060210"
  }, 
  {
    "_type": "TempBasalDuration", 
    "_description": "TempBasalDuration 2016-03-02T06:22:25 head[2], body[0] op[0x16]", 
    "timestamp": "2016-03-02T06:22:25-08:00", 
    "_body": "", 
    "_head": "1600", 
    "duration (min)": 0, 
    "_date": "19d6064210"
  }, 
  {
    "_type": "TempBasal", 
    "temp": "absolute", 
    "_description": "TempBasal 2016-03-02T06:22:25 head[2], body[1] op[0x33]", 
    "timestamp": "2016-03-02T06:22:25-08:00", 
    "_body": "00", 
    "_head": "3300", 
    "rate": 0.0, 
    "_date": "19d6064210"
  }, 
  {
    "_type": "BasalProfileStart", 
    "_description": "BasalProfileStart 2016-03-02T06:22:23 head[2], body[3] op[0x7b]", 
    "timestamp": "2016-03-02T06:22:23-08:00", 
    "_body": "091000", 
    "profile_index": 3, 
    "_head": "7b03", 
    "rate": 0.4, 
    "offset": 16200000, 
    "_date": "17d6060210"
  }, 
  {
    "_type": "TempBasalDuration", 
    "_description": "TempBasalDuration 2016-03-02T06:22:23 head[2], body[0] op[0x16]", 
    "timestamp": "2016-03-02T06:22:23-08:00", 
    "_body": "", 
    "_head": "1600", 
    "duration (min)": 0, 
    "_date": "17d6064210"
  }, 
  {
    "_type": "TempBasal", 
    "temp": "absolute", 
    "_description": "TempBasal 2016-03-02T06:22:23 head[2], body[1] op[0x33]", 
    "timestamp": "2016-03-02T06:22:23-08:00", 
    "_body": "00", 
    "_head": "3300", 
    "rate": 0.0, 
    "_date": "17d6064210"
  }, 
  {
    "_type": "TempBasalDuration", 
    "_description": "TempBasalDuration 2016-03-02T06:12:47 head[2], body[0] op[0x16]", 
    "timestamp": "2016-03-02T06:12:47-08:00", 
    "_body": "", 
    "_head": "1601", 
    "duration (min)": 30, 
    "_date": "2fcc064210"
  }, 
  {
    "_type": "TempBasal", 
    "temp": "absolute", 
    "_description": "TempBasal 2016-03-02T06:12:47 head[2], body[1] op[0x33]", 
    "timestamp": "2016-03-02T06:12:47-08:00", 
    "_body": "00", 
    "_head": "331a", 
    "rate": 0.65, 
    "_date": "2fcc064210"
  }, 
  {
    "_type": "TempBasalDuration", 
    "_description": "TempBasalDuration 2016-03-02T06:12:45 head[2], body[0] op[0x16]", 
    "timestamp": "2016-03-02T06:12:45-08:00", 
    "_body": "", 
    "_head": "1601", 
    "duration (min)": 30, 
    "_date": "2dcc064210"
  }, 
  {
    "_type": "TempBasal", 
    "temp": "absolute", 
    "_description": "TempBasal 2016-03-02T06:12:45 head[2], body[1] op[0x33]", 
    "timestamp": "2016-03-02T06:12:45-08:00", 
    "_body": "00", 
    "_head": "331a", 
    "rate": 0.65, 
    "_date": "2dcc064210"
  }, 
  {
    "_type": "TempBasalDuration", 
    "_description": "TempBasalDuration 2016-03-02T06:12:44 head[2], body[0] op[0x16]", 
    "timestamp": "2016-03-02T06:12:44-08:00", 
    "_body": "", 
    "_head": "1601", 
    "duration (min)": 30, 
    "_date": "2ccc064210"
  }, 
  {
    "_type": "TempBasal", 
    "temp": "absolute", 
    "_description": "TempBasal 2016-03-02T06:12:44 head[2], body[1] op[0x33]", 
    "timestamp": "2016-03-02T06:12:44-08:00", 
    "_body": "00", 
    "_head": "331a", 
    "rate": 0.65, 
    "_date": "2ccc064210"
  }, 
  {
    "_type": "BasalProfileStart", 
    "_description": "BasalProfileStart 2016-03-02T05:52:34 head[2], body[3] op[0x7b]", 
    "timestamp": "2016-03-02T05:52:34-08:00", 
    "_body": "091000", 
    "profile_index": 3, 
    "_head": "7b03", 
    "rate": 0.4, 
    "offset": 16200000, 
    "_date": "22f4050210"
  }, 
  {
    "_type": "TempBasalDuration", 
    "_description": "TempBasalDuration 2016-03-02T05:52:34 head[2], body[0] op[0x16]", 
    "timestamp": "2016-03-02T05:52:34-08:00", 
    "_body": "", 
    "_head": "1600", 
    "duration (min)": 0, 
    "_date": "22f4054210"
  }, 
  {
    "_type": "TempBasal", 
    "temp": "absolute", 
    "_description": "TempBasal 2016-03-02T05:52:34 head[2], body[1] op[0x33]", 
    "timestamp": "2016-03-02T05:52:34-08:00", 
    "_body": "00", 
    "_head": "3300", 
    "rate": 0.0, 
    "_date": "22f4054210"
  }, 
  {
    "_type": "BasalProfileStart", 
    "_description": "BasalProfileStart 2016-03-02T05:52:32 head[2], body[3] op[0x7b]", 
    "timestamp": "2016-03-02T05:52:32-08:00", 
    "_body": "091000", 
    "profile_index": 3, 
    "_head": "7b03", 
    "rate": 0.4, 
    "offset": 16200000, 
    "_date": "20f4050210"
  }, 
  {
    "_type": "TempBasalDuration", 
    "_description": "TempBasalDuration 2016-03-02T05:52:32 head[2], body[0] op[0x16]", 
    "timestamp": "2016-03-02T05:52:32-08:00", 
    "_body": "", 
    "_head": "1600", 
    "duration (min)": 0, 
    "_date": "20f4054210"
  }, 
  {
    "_type": "TempBasal", 
    "temp": "absolute", 
    "_description": "TempBasal 2016-03-02T05:52:32 head[2], body[1] op[0x33]", 
    "timestamp": "2016-03-02T05:52:32-08:00", 
    "_body": "00", 
    "_head": "3300", 
    "rate": 0.0, 
    "_date": "20f4054210"
  }, 
  {
    "_type": "BasalProfileStart", 
    "_description": "BasalProfileStart 2016-03-02T05:52:30 head[2], body[3] op[0x7b]", 
    "timestamp": "2016-03-02T05:52:30-08:00", 
    "_body": "091000", 
    "profile_index": 3, 
    "_head": "7b03", 
    "rate": 0.4, 
    "offset": 16200000, 
    "_date": "1ef4050210"
  }, 
  {
    "_type": "TempBasalDuration", 
    "_description": "TempBasalDuration 2016-03-02T05:52:30 head[2], body[0] op[0x16]", 
    "timestamp": "2016-03-02T05:52:30-08:00", 
    "_body": "", 
    "_head": "1600", 
    "duration (min)": 0, 
    "_date": "1ef4054210"
  }, 
  {
    "_type": "TempBasal", 
    "temp": "absolute", 
    "_description": "TempBasal 2016-03-02T05:52:30 head[2], body[1] op[0x33]", 
    "timestamp": "2016-03-02T05:52:30-08:00", 
    "_body": "00", 
    "_head": "3300", 
    "rate": 0.0, 
    "_date": "1ef4054210"
  }, 
  {
    "_type": "TempBasalDuration", 
    "_description": "TempBasalDuration 2016-03-02T05:41:50 head[2], body[0] op[0x16]", 
    "timestamp": "2016-03-02T05:41:50-08:00", 
    "_body": "", 
    "_head": "1601", 
    "duration (min)": 30, 
    "_date": "32e9054210"
  }, 
  {
    "_type": "TempBasal", 
    "temp": "absolute", 
    "_description": "TempBasal 2016-03-02T05:41:50 head[2], body[1] op[0x33]", 
    "timestamp": "2016-03-02T05:41:50-08:00", 
    "_body": "00", 
    "_head": "3300", 
    "rate": 0.0, 
    "_date": "32e9054210"
  }, 
  {
    "_type": "TempBasalDuration", 
    "_description": "TempBasalDuration 2016-03-02T05:41:48 head[2], body[0] op[0x16]", 
    "timestamp": "2016-03-02T05:41:48-08:00", 
    "_body": "", 
    "_head": "1601", 
    "duration (min)": 30, 
    "_date": "30e9054210"
  }, 
  {
    "_type": "TempBasal", 
    "temp": "absolute", 
    "_description": "TempBasal 2016-03-02T05:41:48 head[2], body[1] op[0x33]", 
    "timestamp": "2016-03-02T05:41:48-08:00", 
    "_body": "00", 
    "_head": "3300", 
    "rate": 0.0, 
    "_date": "30e9054210"
  }, 
  {
    "_type": "TempBasalDuration", 
    "_description": "TempBasalDuration 2016-03-02T05:41:47 head[2], body[0] op[0x16]", 
    "timestamp": "2016-03-02T05:41:47-08:00", 
    "_body": "", 
    "_head": "1601", 
    "duration (min)": 30, 
    "_date": "2fe9054210"
  }, 
  {
    "_type": "TempBasal", 
    "temp": "absolute", 
    "_description": "TempBasal 2016-03-02T05:41:47 head[2], body[1] op[0x33]", 
    "timestamp": "2016-03-02T05:41:47-08:00", 
    "_body": "00", 
    "_head": "3300", 
    "rate": 0.0, 
    "_date": "2fe9054210"
  }, 
  {
    "_type": "TempBasalDuration", 
    "_description": "TempBasalDuration 2016-03-02T05:36:52 head[2], body[0] op[0x16]", 
    "timestamp": "2016-03-02T05:36:52-08:00", 
    "_body": "", 
    "_head": "1601", 
    "duration (min)": 30, 
    "_date": "34e4054210"
  }, 
  {
    "_type": "TempBasal", 
    "temp": "absolute", 
    "_description": "TempBasal 2016-03-02T05:36:52 head[2], body[1] op[0x33]", 
    "timestamp": "2016-03-02T05:36:52-08:00", 
    "_body": "00", 
    "_head": "3300", 
    "rate": 0.0, 
    "_date": "34e4054210"
  }, 
  {
    "_type": "TempBasalDuration", 
    "_description": "TempBasalDuration 2016-03-02T05:36:49 head[2], body[0] op[0x16]", 
    "timestamp": "2016-03-02T05:36:49-08:00", 
    "_body": "", 
    "_head": "1601", 
    "duration (min)": 30, 
    "_date": "31e4054210"
  }, 
  {
    "_type": "TempBasal", 
    "temp": "absolute", 
    "_description": "TempBasal 2016-03-02T05:36:49 head[2], body[1] op[0x33]", 
    "timestamp": "2016-03-02T05:36:49-08:00", 
    "_body": "00", 
    "_head": "3300", 
    "rate": 0.0, 
    "_date": "31e4054210"
  }, 
  {
    "_type": "TempBasalDuration", 
    "_description": "TempBasalDuration 2016-03-02T05:36:48 head[2], body[0] op[0x16]", 
    "timestamp": "2016-03-02T05:36:48-08:00", 
    "_body": "", 
    "_head": "1601", 
    "duration (min)": 30, 
    "_date": "30e4054210"
  }, 
  {
    "_type": "TempBasal", 
    "temp": "absolute", 
    "_description": "TempBasal 2016-03-02T05:36:48 head[2], body[1] op[0x33]", 
    "timestamp": "2016-03-02T05:36:48-08:00", 
    "_body": "00", 
    "_head": "3300", 
    "rate": 0.0, 
    "_date": "30e4054210"
  }, 
  {
    "_type": "TempBasalDuration", 
    "_description": "TempBasalDuration 2016-03-02T05:22:14 head[2], body[0] op[0x16]", 
    "timestamp": "2016-03-02T05:22:14-08:00", 
    "_body": "", 
    "_head": "1601", 
    "duration (min)": 30, 
    "_date": "0ed6054210"
  }, 
  {
    "_type": "TempBasal", 
    "temp": "absolute", 
    "_description": "TempBasal 2016-03-02T05:22:14 head[2], body[1] op[0x33]", 
    "timestamp": "2016-03-02T05:22:14-08:00", 
    "_body": "00", 
    "_head": "331a", 
    "rate": 0.65, 
    "_date": "0ed6054210"
  }, 
  {
    "_type": "TempBasalDuration", 
    "_description": "TempBasalDuration 2016-03-02T05:22:11 head[2], body[0] op[0x16]", 
    "timestamp": "2016-03-02T05:22:11-08:00", 
    "_body": "", 
    "_head": "1601", 
    "duration (min)": 30, 
    "_date": "0bd6054210"
  }, 
  {
    "_type": "TempBasal", 
    "temp": "absolute", 
    "_description": "TempBasal 2016-03-02T05:22:11 head[2], body[1] op[0x33]", 
    "timestamp": "2016-03-02T05:22:11-08:00", 
    "_body": "00", 
    "_head": "331a", 
    "rate": 0.65, 
    "_date": "0bd6054210"
  }, 
  {
    "_type": "TempBasalDuration", 
    "_description": "TempBasalDuration 2016-03-02T05:22:10 head[2], body[0] op[0x16]", 
    "timestamp": "2016-03-02T05:22:10-08:00", 
    "_body": "", 
    "_head": "1601", 
    "duration (min)": 30, 
    "_date": "0ad6054210"
  }, 
  {
    "_type": "TempBasal", 
    "temp": "absolute", 
    "_description": "TempBasal 2016-03-02T05:22:10 head[2], body[1] op[0x33]", 
    "timestamp": "2016-03-02T05:22:10-08:00", 
    "_body": "00", 
    "_head": "331a", 
    "rate": 0.65, 
    "_date": "0ad6054210"
  }, 
  {
    "_type": "BasalProfileStart", 
    "_description": "BasalProfileStart 2016-03-02T05:11:54 head[2], body[3] op[0x7b]", 
    "timestamp": "2016-03-02T05:11:54-08:00", 
    "_body": "091000", 
    "profile_index": 3, 
    "_head": "7b03", 
    "rate": 0.4, 
    "offset": 16200000, 
    "_date": "36cb050210"
  }, 
  {
    "_type": "TempBasalDuration", 
    "_description": "TempBasalDuration 2016-03-02T05:11:54 head[2], body[0] op[0x16]", 
    "timestamp": "2016-03-02T05:11:54-08:00", 
    "_body": "", 
    "_head": "1600", 
    "duration (min)": 0, 
    "_date": "36cb054210"
  }, 
  {
    "_type": "TempBasal", 
    "temp": "absolute", 
    "_description": "TempBasal 2016-03-02T05:11:54 head[2], body[1] op[0x33]", 
    "timestamp": "2016-03-02T05:11:54-08:00", 
    "_body": "00", 
    "_head": "3300", 
    "rate": 0.0, 
    "_date": "36cb054210"
  }, 
  {
    "_type": "BasalProfileStart", 
    "_description": "BasalProfileStart 2016-03-02T05:11:51 head[2], body[3] op[0x7b]", 
    "timestamp": "2016-03-02T05:11:51-08:00", 
    "_body": "091000", 
    "profile_index": 3, 
    "_head": "7b03", 
    "rate": 0.4, 
    "offset": 16200000, 
    "_date": "33cb050210"
  }, 
  {
    "_type": "TempBasalDuration", 
    "_description": "TempBasalDuration 2016-03-02T05:11:51 head[2], body[0] op[0x16]", 
    "timestamp": "2016-03-02T05:11:51-08:00", 
    "_body": "", 
    "_head": "1600", 
    "duration (min)": 0, 
    "_date": "33cb054210"
  }, 
  {
    "_type": "TempBasal", 
    "temp": "absolute", 
    "_description": "TempBasal 2016-03-02T05:11:51 head[2], body[1] op[0x33]", 
    "timestamp": "2016-03-02T05:11:51-08:00", 
    "_body": "00", 
    "_head": "3300", 
    "rate": 0.0, 
    "_date": "33cb054210"
  }, 
  {
    "_type": "BasalProfileStart", 
    "_description": "BasalProfileStart 2016-03-02T05:11:49 head[2], body[3] op[0x7b]", 
    "timestamp": "2016-03-02T05:11:49-08:00", 
    "_body": "091000", 
    "profile_index": 3, 
    "_head": "7b03", 
    "rate": 0.4, 
    "offset": 16200000, 
    "_date": "31cb050210"
  }, 
  {
    "_type": "TempBasalDuration", 
    "_description": "TempBasalDuration 2016-03-02T05:11:49 head[2], body[0] op[0x16]", 
    "timestamp": "2016-03-02T05:11:49-08:00", 
    "_body": "", 
    "_head": "1600", 
    "duration (min)": 0, 
    "_date": "31cb054210"
  }, 
  {
    "_type": "TempBasal", 
    "temp": "absolute", 
    "_description": "TempBasal 2016-03-02T05:11:49 head[2], body[1] op[0x33]", 
    "timestamp": "2016-03-02T05:11:49-08:00", 
    "_body": "00", 
    "_head": "3300", 
    "rate": 0.0, 
    "_date": "31cb054210"
  }, 
  {
    "_type": "TempBasalDuration", 
    "_description": "TempBasalDuration 2016-03-02T05:01:53 head[2], body[0] op[0x16]", 
    "timestamp": "2016-03-02T05:01:53-08:00", 
    "_body": "", 
    "_head": "1601", 
    "duration (min)": 30, 
    "_date": "35c1054210"
  }, 
  {
    "_type": "TempBasal", 
    "temp": "absolute", 
    "_description": "TempBasal 2016-03-02T05:01:53 head[2], body[1] op[0x33]", 
    "timestamp": "2016-03-02T05:01:53-08:00", 
    "_body": "00", 
    "_head": "331b", 
    "rate": 0.675, 
    "_date": "35c1054210"
  }, 
  {
    "_type": "TempBasalDuration", 
    "_description": "TempBasalDuration 2016-03-02T05:01:46 head[2], body[0] op[0x16]", 
    "timestamp": "2016-03-02T05:01:46-08:00", 
    "_body": "", 
    "_head": "1601", 
    "duration (min)": 30, 
    "_date": "2ec1054210"
  }, 
  {
    "_type": "TempBasal", 
    "temp": "absolute", 
    "_description": "TempBasal 2016-03-02T05:01:46 head[2], body[1] op[0x33]", 
    "timestamp": "2016-03-02T05:01:46-08:00", 
    "_body": "00", 
    "_head": "331b", 
    "rate": 0.675, 
    "_date": "2ec1054210"
  }, 
  {
    "_type": "TempBasalDuration", 
    "_description": "TempBasalDuration 2016-03-02T05:01:45 head[2], body[0] op[0x16]", 
    "timestamp": "2016-03-02T05:01:45-08:00", 
    "_body": "", 
    "_head": "1601", 
    "duration (min)": 30, 
    "_date": "2dc1054210"
  }, 
  {
    "_type": "TempBasal", 
    "temp": "absolute", 
    "_description": "TempBasal 2016-03-02T05:01:45 head[2], body[1] op[0x33]", 
    "timestamp": "2016-03-02T05:01:45-08:00", 
    "_body": "00", 
    "_head": "331b", 
    "rate": 0.675, 
    "_date": "2dc1054210"
  }
]