{
  "device": "openaps://indy-e3", 
  "pump": {
    "battery": {
      "status": "normal", 
      "voltage": 1.53
    }, 
    "status": {
      "status": "normal", 
      "timestamp": "2016-03-11T18:37:51.000Z", 
      "bolusing": false, 
      "suspended": false
    }, 
    "reservoir": 113.025, 
    "clock": "2016-03-11T10:37:31-08:00"
  }, 
  "openaps": {
    "suggested": {
      "bg": 91, 
      "temp": "absolute", 
      "snoozeBG": 154, 
      "timestamp": "2016-03-11T18:36:09.000Z", 
      "reason": "Eventual BG 104<110, but Delta +8 > Exp. Delta -2.1; no temp to cancel", 
      "eventualBG": 104, 
      "mealAssist": "Off: Carbs: 42 Boluses: 4.5 Target: 115 Deviation: 23 BGI: -2.4", 
      "tick": "+8"
    }, 
    "iob": {
      "netbasalinsulin": -0.05, 
      "timestamp": "2016-03-11T18:36:08.000Z", 
      "basaliob": -0.646, 
      "activity": 0.006, 
      "bolussnooze": 0.417, 
      "iob": 0.12
    }, 
    "enacted": {
      "requested": {
        "duration": 0, 
        "rate": 0, 
        "temp": "absolute"
      }, 
      "bg": 83, 
      "temp": "absolute", 
      "snoozeBG": 144, 
      "timestamp": "2016-03-11T18:31:34.000Z", 
      "reason": "Eventual BG 85<110, but Delta +8 > Exp. Delta -2.2; cancel", 
      "rate": 0, 
      "eventualBG": 85, 
      "recieved": true, 
      "duration": 0, 
      "mealAssist": "Off: Carbs: 42 Boluses: 4.5 Target: 115 Deviation: 14 BGI: -3.08", 
      "tick": "+8"
    }
  }, 
  "mmtune": {
    "scanDetails": [
      [
        "916.540", 
        5, 
        -90
      ], 
      [
        "916.560", 
        5, 
        -80
      ], 
      [
        "916.580", 
        5, 
        -79
      ], 
      [
        "916.600", 
        5, 
        -78
      ], 
      [
        "916.620", 
        5, 
        -78
      ], 
      [
        "916.640", 
        5, 
        -81
      ], 
      [
        "916.660", 
        5, 
        -81
      ], 
      [
        "916.680", 
        5, 
        -82
      ], 
      [
        "916.700", 
        5, 
        -91
      ]
    ], 
    "setFreq": 916.62, 
    "timestamp": "2016-03-11T18:37:35.000Z", 
    "usedDefault": false
  }
}